minty_infra_misc/__init__.py
minty_infra_misc/py.typed
minty_infra_misc-2.0.1.dist-info/METADATA
minty_infra_misc-2.0.1.dist-info/WHEEL
minty_infra_misc-2.0.1.dist-info/top_level.txt
minty_infra_misc-2.0.1.dist-info/RECORD
