Metadata-Version: 2.1
Name: minty-infra-misc
Version: 2.0.1
Summary: Collection of infrastructure wrapper classes for Minty
Home-page: https://gitlab.com/minty-python/minty-infra-misc
Author: Martijn van de Streek
Author-email: martijn@mintlab.nl
License: EUPL license
Keywords: minty_infra_misc
Platform: UNKNOWN
Classifier: Development Status :: 2 - Pre-Alpha
Classifier: Intended Audience :: Developers
Classifier: License :: OSI Approved :: European Union Public Licence 1.2 (EUPL 1.2)
Classifier: Natural Language :: English
Classifier: Programming Language :: Python :: 3.6
Classifier: Programming Language :: Python :: 3.7
Requires-Dist: minty (~=3.0)
Requires-Dist: redis (~=4.0)
Provides-Extra: dev
Requires-Dist: bumpversion (~=0.5) ; extra == 'dev'
